{
"meta":{"test_sets":[],"test_metrics":[],"learn_metrics":[{"best_value":"Min","name":"Logloss"}],"launch_mode":"Train","parameters":"","iteration_count":500,"learn_sets":["learn"],"name":"experiment"},
"iterations":[
{"learn":[0.6171525506],"iteration":0,"passed_time":0.3261912314,"remaining_time":162.7694245},
{"learn":[0.5504581485],"iteration":1,"passed_time":0.4529534447,"remaining_time":112.7854077},
{"learn":[0.4923791173],"iteration":2,"passed_time":0.5724224647,"remaining_time":94.83132165},
{"learn":[0.4397379171],"iteration":3,"passed_time":0.6816571984,"remaining_time":84.52549261},
{"learn":[0.399545046],"iteration":4,"passed_time":0.7843020324,"remaining_time":77.64590121},
{"learn":[0.3676389408],"iteration":5,"passed_time":0.8908887572,"remaining_time":73.34984101},
{"learn":[0.3388877822],"iteration":6,"passed_time":1.003821607,"remaining_time":70.69772176},
{"learn":[0.3126414816],"iteration":7,"passed_time":1.107071891,"remaining_time":68.08492132},
{"learn":[0.2912174445],"iteration":8,"passed_time":1.205161897,"remaining_time":65.74827681},
{"learn":[0.2691635411],"iteration":9,"passed_time":1.314743912,"remaining_time":64.4224517},
{"learn":[0.2512983212],"iteration":10,"passed_time":1.416342801,"remaining_time":62.96287541},
{"learn":[0.2365756732],"iteration":11,"passed_time":1.519041684,"remaining_time":61.77436181},
{"learn":[0.2216439581],"iteration":12,"passed_time":1.627520364,"remaining_time":60.9694167},
{"learn":[0.2094113563],"iteration":13,"passed_time":1.728056807,"remaining_time":59.98825773},
{"learn":[0.2001441919],"iteration":14,"passed_time":1.824580359,"remaining_time":58.99476495},
{"learn":[0.1923348596],"iteration":15,"passed_time":1.93177253,"remaining_time":58.43611904},
{"learn":[0.1856726074],"iteration":16,"passed_time":2.04154386,"remaining_time":58.00386379},
{"learn":[0.1805972197],"iteration":17,"passed_time":2.140564547,"remaining_time":57.31956177},
{"learn":[0.1747721961],"iteration":18,"passed_time":2.241418954,"remaining_time":56.74329037},
{"learn":[0.1681034598],"iteration":19,"passed_time":2.350999098,"remaining_time":56.42397835},
{"learn":[0.1622157231],"iteration":20,"passed_time":2.447374157,"remaining_time":55.8234391},
{"learn":[0.1573799832],"iteration":21,"passed_time":2.547130132,"remaining_time":55.34219104},
{"learn":[0.152198896],"iteration":22,"passed_time":2.656096221,"remaining_time":55.08512598},
{"learn":[0.149064179],"iteration":23,"passed_time":2.763701778,"remaining_time":54.8134186},
{"learn":[0.1451654022],"iteration":24,"passed_time":2.868780453,"remaining_time":54.50682861},
{"learn":[0.1416549155],"iteration":25,"passed_time":2.97575902,"remaining_time":54.25037598},
{"learn":[0.1388592798],"iteration":26,"passed_time":3.087984473,"remaining_time":54.09691318},
{"learn":[0.1359262726],"iteration":27,"passed_time":3.203258169,"remaining_time":53.99778056},
{"learn":[0.1330075849],"iteration":28,"passed_time":3.31008785,"remaining_time":53.76039232},
{"learn":[0.130737615],"iteration":29,"passed_time":3.408537241,"remaining_time":53.40041678},
{"learn":[0.1280923772],"iteration":30,"passed_time":3.507338013,"remaining_time":53.06262994},
{"learn":[0.125002668],"iteration":31,"passed_time":3.614086087,"remaining_time":52.85600902},
{"learn":[0.1227087578],"iteration":32,"passed_time":3.718057491,"remaining_time":52.61614692},
{"learn":[0.1206793906],"iteration":33,"passed_time":3.824306585,"remaining_time":52.41549614},
{"learn":[0.1190954062],"iteration":34,"passed_time":3.928365337,"remaining_time":52.19113948},
{"learn":[0.1174261309],"iteration":35,"passed_time":4.035172253,"remaining_time":52.00888681},
{"learn":[0.1155719594],"iteration":36,"passed_time":4.132660106,"remaining_time":51.71409808},
{"learn":[0.1138994834],"iteration":37,"passed_time":4.223881567,"remaining_time":51.35350748},
{"learn":[0.1110931603],"iteration":38,"passed_time":4.336090831,"remaining_time":51.25481725},
{"learn":[0.1096683898],"iteration":39,"passed_time":4.434356715,"remaining_time":50.99510222},
{"learn":[0.107942747],"iteration":40,"passed_time":4.524227396,"remaining_time":50.64927744},
{"learn":[0.1066485347],"iteration":41,"passed_time":4.628925481,"remaining_time":50.47733024},
{"learn":[0.1049764104],"iteration":42,"passed_time":4.734348472,"remaining_time":50.31621516},
{"learn":[0.1041362139],"iteration":43,"passed_time":4.92918716,"remaining_time":51.0843033},
{"learn":[0.1028034037],"iteration":44,"passed_time":5.095819581,"remaining_time":51.52439799},
{"learn":[0.1015269196],"iteration":45,"passed_time":5.185701202,"remaining_time":51.18061621},
{"learn":[0.1000919748],"iteration":46,"passed_time":5.280101746,"remaining_time":50.89119342},
{"learn":[0.09881840282],"iteration":47,"passed_time":5.373452246,"remaining_time":50.60000865},
{"learn":[0.09790804588],"iteration":48,"passed_time":5.464742676,"remaining_time":50.29793769},
{"learn":[0.09675458488],"iteration":49,"passed_time":5.557527931,"remaining_time":50.01775138},
{"learn":[0.09601703812],"iteration":50,"passed_time":5.651265358,"remaining_time":49.75329697},
{"learn":[0.09475109243],"iteration":51,"passed_time":5.751109837,"remaining_time":49.54802321},
{"learn":[0.09374038955],"iteration":52,"passed_time":5.839928453,"remaining_time":49.2537362},
{"learn":[0.09264196157],"iteration":53,"passed_time":5.937955584,"remaining_time":49.04311464},
{"learn":[0.09213472114],"iteration":54,"passed_time":6.035915781,"remaining_time":48.83604587},
{"learn":[0.09097233349],"iteration":55,"passed_time":6.147303993,"remaining_time":48.7393388},
{"learn":[0.09005263299],"iteration":56,"passed_time":6.249478512,"remaining_time":48.57050843},
{"learn":[0.08930863927],"iteration":57,"passed_time":6.352274598,"remaining_time":48.40871332},
{"learn":[0.0881888345],"iteration":58,"passed_time":6.45356501,"remaining_time":48.23766389},
{"learn":[0.087165517],"iteration":59,"passed_time":6.554389699,"remaining_time":48.06552446},
{"learn":[0.08657234735],"iteration":60,"passed_time":6.652722944,"remaining_time":47.87779299},
{"learn":[0.08603368623],"iteration":61,"passed_time":6.75591441,"remaining_time":47.72726632},
{"learn":[0.08521752412],"iteration":62,"passed_time":6.855354673,"remaining_time":47.5522221},
{"learn":[0.08415069063],"iteration":63,"passed_time":6.957999178,"remaining_time":47.4013694},
{"learn":[0.08349337872],"iteration":64,"passed_time":7.056381123,"remaining_time":47.22347367},
{"learn":[0.0827627129],"iteration":65,"passed_time":7.160066318,"remaining_time":47.08286033},
{"learn":[0.08196551979],"iteration":66,"passed_time":7.271614276,"remaining_time":46.9941639},
{"learn":[0.08110726205],"iteration":67,"passed_time":7.382505078,"remaining_time":46.90062049},
{"learn":[0.08012077926],"iteration":68,"passed_time":7.496054111,"remaining_time":46.82317858},
{"learn":[0.07944856288],"iteration":69,"passed_time":7.602061569,"remaining_time":46.69837821},
{"learn":[0.07887399137],"iteration":70,"passed_time":7.702793204,"remaining_time":46.54222936},
{"learn":[0.07823603433],"iteration":71,"passed_time":7.805338002,"remaining_time":46.39839812},
{"learn":[0.07740937624],"iteration":72,"passed_time":7.908934957,"remaining_time":46.26185242},
{"learn":[0.07669993669],"iteration":73,"passed_time":8.009169761,"remaining_time":46.10684214},
{"learn":[0.07616510527],"iteration":74,"passed_time":8.110235646,"remaining_time":45.95800199},
{"learn":[0.07538365458],"iteration":75,"passed_time":8.207309315,"remaining_time":45.7881467},
{"learn":[0.0741476099],"iteration":76,"passed_time":8.308528852,"remaining_time":45.6429572},
{"learn":[0.07349710393],"iteration":77,"passed_time":8.411984903,"remaining_time":45.51099524},
{"learn":[0.07280667735],"iteration":78,"passed_time":8.512356027,"remaining_time":45.36331503},
{"learn":[0.07215921176],"iteration":79,"passed_time":8.607957476,"remaining_time":45.19177675},
{"learn":[0.0717353138],"iteration":80,"passed_time":8.705275506,"remaining_time":45.03099305},
{"learn":[0.07094635837],"iteration":81,"passed_time":8.80834554,"remaining_time":44.90107849},
{"learn":[0.07013950154],"iteration":82,"passed_time":8.916497594,"remaining_time":44.79734334},
{"learn":[0.06936984356],"iteration":83,"passed_time":9.024602605,"remaining_time":44.69327005},
{"learn":[0.06882389806],"iteration":84,"passed_time":9.154388717,"remaining_time":44.69495668},
{"learn":[0.06826058443],"iteration":85,"passed_time":9.269527918,"remaining_time":44.62307626},
{"learn":[0.0678427243],"iteration":86,"passed_time":9.368730093,"remaining_time":44.4745463},
{"learn":[0.06747270797],"iteration":87,"passed_time":9.474981983,"remaining_time":44.36014292},
{"learn":[0.06703171604],"iteration":88,"passed_time":9.582776832,"remaining_time":44.25304807},
{"learn":[0.0664491872],"iteration":89,"passed_time":9.684216756,"remaining_time":44.11698744},
{"learn":[0.06573941919],"iteration":90,"passed_time":9.781377794,"remaining_time":43.96245624},
{"learn":[0.06516946153],"iteration":91,"passed_time":9.882813788,"remaining_time":43.82813071},
{"learn":[0.06466275697],"iteration":92,"passed_time":10.00342146,"remaining_time":43.77841433},
{"learn":[0.06413854411],"iteration":93,"passed_time":10.12177557,"remaining_time":43.71745619},
{"learn":[0.06347555232],"iteration":94,"passed_time":10.22739402,"remaining_time":43.60099556},
{"learn":[0.06295912714],"iteration":95,"passed_time":10.35170134,"remaining_time":43.56340982},
{"learn":[0.06244227523],"iteration":96,"passed_time":10.45230986,"remaining_time":43.42557601},
{"learn":[0.06213342544],"iteration":97,"passed_time":10.5438473,"remaining_time":43.251292},
{"learn":[0.06158675578],"iteration":98,"passed_time":10.64961338,"remaining_time":43.1363128},
{"learn":[0.06111764423],"iteration":99,"passed_time":10.74721139,"remaining_time":42.98884557},
{"learn":[0.06046606652],"iteration":100,"passed_time":10.85758868,"remaining_time":42.89285034},
{"learn":[0.06002889653],"iteration":101,"passed_time":10.96458839,"remaining_time":42.78339392},
{"learn":[0.05972824614],"iteration":102,"passed_time":11.06958986,"remaining_time":42.66628325},
{"learn":[0.05928542625],"iteration":103,"passed_time":11.18592523,"remaining_time":42.59256146},
{"learn":[0.05878025223],"iteration":104,"passed_time":11.29146024,"remaining_time":42.47739805},
{"learn":[0.05843941019],"iteration":105,"passed_time":11.39572959,"remaining_time":42.35771187},
{"learn":[0.05787488879],"iteration":106,"passed_time":11.49710554,"remaining_time":42.22768672},
{"learn":[0.05749002437],"iteration":107,"passed_time":11.584407,"remaining_time":42.04710688},
{"learn":[0.05733857184],"iteration":108,"passed_time":11.68603182,"remaining_time":41.91961875},
{"learn":[0.05697377092],"iteration":109,"passed_time":11.78304235,"remaining_time":41.77624107},
{"learn":[0.05649711014],"iteration":110,"passed_time":11.87509423,"remaining_time":41.61632123},
{"learn":[0.05626024822],"iteration":111,"passed_time":11.97256584,"remaining_time":41.47638881},
{"learn":[0.05576111047],"iteration":112,"passed_time":12.08220332,"remaining_time":41.37887332},
{"learn":[0.05542879473],"iteration":113,"passed_time":12.19758857,"remaining_time":41.30060691},
{"learn":[0.05507578291],"iteration":114,"passed_time":12.30165715,"remaining_time":41.18380873},
{"learn":[0.05475899182],"iteration":115,"passed_time":12.39764414,"remaining_time":41.04047716},
{"learn":[0.05414590558],"iteration":116,"passed_time":12.50208666,"remaining_time":40.92563413},
{"learn":[0.05386066605],"iteration":117,"passed_time":12.60348568,"remaining_time":40.80111465},
{"learn":[0.05338996189],"iteration":118,"passed_time":12.71023936,"remaining_time":40.69412771},
{"learn":[0.05308661458],"iteration":119,"passed_time":12.81105832,"remaining_time":40.56835134},
{"learn":[0.05272454162],"iteration":120,"passed_time":12.91801608,"remaining_time":40.46221567},
{"learn":[0.05236221055],"iteration":121,"passed_time":13.03582772,"remaining_time":40.38969571},
{"learn":[0.0519053324],"iteration":122,"passed_time":13.13837633,"remaining_time":40.26965752},
{"learn":[0.05168986951],"iteration":123,"passed_time":13.2410444,"remaining_time":40.15026367},
{"learn":[0.05111739336],"iteration":124,"passed_time":13.34578955,"remaining_time":40.03736864},
{"learn":[0.05089651748],"iteration":125,"passed_time":13.45637731,"remaining_time":39.94194535},
{"learn":[0.05060860637],"iteration":126,"passed_time":13.562665,"remaining_time":39.83365391},
{"learn":[0.05003614212],"iteration":127,"passed_time":13.66604156,"remaining_time":39.71693327},
{"learn":[0.04963703117],"iteration":128,"passed_time":13.77944733,"remaining_time":39.62926325},
{"learn":[0.04928198966],"iteration":129,"passed_time":13.87428956,"remaining_time":39.48836258},
{"learn":[0.0489616213],"iteration":130,"passed_time":13.96577274,"remaining_time":39.33870338},
{"learn":[0.04865544309],"iteration":131,"passed_time":14.05785204,"remaining_time":39.19158751},
{"learn":[0.04834528778],"iteration":132,"passed_time":14.16616744,"remaining_time":39.09010112},
{"learn":[0.04812108392],"iteration":133,"passed_time":14.25964253,"remaining_time":38.94797884},
{"learn":[0.04755243127],"iteration":134,"passed_time":14.35987273,"remaining_time":38.82484108},
{"learn":[0.04705426284],"iteration":135,"passed_time":14.45645355,"remaining_time":38.69227275},
{"learn":[0.04671429495],"iteration":136,"passed_time":14.56396207,"remaining_time":38.58918417},
{"learn":[0.04641020591],"iteration":137,"passed_time":14.66189756,"remaining_time":38.46091968},
{"learn":[0.0461786018],"iteration":138,"passed_time":14.77145371,"remaining_time":38.36327186},
{"learn":[0.04591471009],"iteration":139,"passed_time":14.87950588,"remaining_time":38.26158655},
{"learn":[0.04565317704],"iteration":140,"passed_time":14.98788602,"remaining_time":38.16064596},
{"learn":[0.04538208991],"iteration":141,"passed_time":15.14162051,"remaining_time":38.17394466},
{"learn":[0.0451672746],"iteration":142,"passed_time":15.26732268,"remaining_time":38.11492445},
{"learn":[0.04486394384],"iteration":143,"passed_time":15.3967326,"remaining_time":38.06414447},
{"learn":[0.04475193347],"iteration":144,"passed_time":15.519858,"remaining_time":37.99689372},
{"learn":[0.04446376736],"iteration":145,"passed_time":15.63480781,"remaining_time":37.90905454},
{"learn":[0.04420888713],"iteration":146,"passed_time":15.78896419,"remaining_time":37.91499563},
{"learn":[0.04396783706],"iteration":147,"passed_time":15.91887953,"remaining_time":37.86111889},
{"learn":[0.04358673096],"iteration":148,"passed_time":16.03364677,"remaining_time":37.77053702},
{"learn":[0.04334461225],"iteration":149,"passed_time":16.1501799,"remaining_time":37.6837531},
{"learn":[0.04305709735],"iteration":150,"passed_time":16.25838644,"remaining_time":37.57733025},
{"learn":[0.04259714987],"iteration":151,"passed_time":16.35702071,"remaining_time":37.44896846},
{"learn":[0.04230913376],"iteration":152,"passed_time":16.45611789,"remaining_time":37.32204515},
{"learn":[0.04212796641],"iteration":153,"passed_time":16.5563064,"remaining_time":37.19793516},
{"learn":[0.04195302724],"iteration":154,"passed_time":16.66320547,"remaining_time":37.08907025},
{"learn":[0.04166889048],"iteration":155,"passed_time":16.77000221,"remaining_time":36.98000487},
{"learn":[0.04151151444],"iteration":156,"passed_time":16.8741988,"remaining_time":36.86528783},
{"learn":[0.04121774964],"iteration":157,"passed_time":16.96818411,"remaining_time":36.72860105},
{"learn":[0.04099277613],"iteration":158,"passed_time":17.0709711,"remaining_time":36.61132795},
{"learn":[0.04079028682],"iteration":159,"passed_time":17.16504521,"remaining_time":36.47572107},
{"learn":[0.04054923054],"iteration":160,"passed_time":17.27258134,"remaining_time":36.36897562},
{"learn":[0.04042365071],"iteration":161,"passed_time":17.39401454,"remaining_time":36.29121551},
{"learn":[0.04021911],"iteration":162,"passed_time":17.51464208,"remaining_time":36.21125387},
{"learn":[0.04012450758],"iteration":163,"passed_time":17.64083432,"remaining_time":36.14219715},
{"learn":[0.04002001591],"iteration":164,"passed_time":17.75214999,"remaining_time":36.04224392},
{"learn":[0.03992291415],"iteration":165,"passed_time":17.87763371,"remaining_time":35.9706606},
{"learn":[0.03966760926],"iteration":166,"passed_time":17.98270118,"remaining_time":35.85772151},
{"learn":[0.03953005206],"iteration":167,"passed_time":18.09862028,"remaining_time":35.76632102},
{"learn":[0.03929123597],"iteration":168,"passed_time":18.20271889,"remaining_time":35.65147901},
{"learn":[0.03898299473],"iteration":169,"passed_time":18.31761543,"remaining_time":35.55772407},
{"learn":[0.03876466732],"iteration":170,"passed_time":18.43869034,"remaining_time":35.4756089},
{"learn":[0.03868450333],"iteration":171,"passed_time":18.54594626,"remaining_time":35.36668822},
{"learn":[0.03838614461],"iteration":172,"passed_time":18.64842864,"remaining_time":35.24876396},
{"learn":[0.03819128211],"iteration":173,"passed_time":18.74966908,"remaining_time":35.12869035},
{"learn":[0.03797491817],"iteration":174,"passed_time":18.84704417,"remaining_time":35.00165346},
{"learn":[0.03778281183],"iteration":175,"passed_time":18.9593667,"remaining_time":34.90247051},
{"learn":[0.03751146711],"iteration":176,"passed_time":19.04820687,"remaining_time":34.76028712},
{"learn":[0.03719396585],"iteration":177,"passed_time":19.14541738,"remaining_time":34.63384492},
{"learn":[0.03696541841],"iteration":178,"passed_time":19.2480458,"remaining_time":34.51744526},
{"learn":[0.03670911291],"iteration":179,"passed_time":19.3517692,"remaining_time":34.40314524},
{"learn":[0.03658424352],"iteration":180,"passed_time":19.45905537,"remaining_time":34.29524123},
{"learn":[0.03636669198],"iteration":181,"passed_time":19.58479347,"remaining_time":34.21958419},
{"learn":[0.03620443777],"iteration":182,"passed_time":19.69040171,"remaining_time":34.10851006},
{"learn":[0.03606995793],"iteration":183,"passed_time":19.79554844,"remaining_time":33.99670275},
{"learn":[0.03585204095],"iteration":184,"passed_time":19.9002,"remaining_time":33.88412433},
{"learn":[0.03575025707],"iteration":185,"passed_time":20.01522053,"remaining_time":33.78913573},
{"learn":[0.03554070373],"iteration":186,"passed_time":20.11471141,"remaining_time":33.66793943},
{"learn":[0.0353459302],"iteration":187,"passed_time":20.22435443,"remaining_time":33.56382224},
{"learn":[0.03509399207],"iteration":188,"passed_time":20.33230434,"remaining_time":33.45686058},
{"learn":[0.03487998807],"iteration":189,"passed_time":20.44491631,"remaining_time":33.35749504},
{"learn":[0.03463699315],"iteration":190,"passed_time":20.5500876,"remaining_time":33.24595323},
{"learn":[0.03451302376],"iteration":191,"passed_time":20.64942134,"remaining_time":33.1251134},
{"learn":[0.03425835561],"iteration":192,"passed_time":20.75213296,"remaining_time":33.00986952},
{"learn":[0.03391697305],"iteration":193,"passed_time":20.86184871,"remaining_time":32.9058026},
{"learn":[0.03382532643],"iteration":194,"passed_time":20.96009813,"remaining_time":32.78374323},
{"learn":[0.03363369958],"iteration":195,"passed_time":21.06078497,"remaining_time":32.66570731},
{"learn":[0.03345263594],"iteration":196,"passed_time":21.19877501,"remaining_time":32.60522247},
{"learn":[0.03335911922],"iteration":197,"passed_time":21.31084583,"remaining_time":32.50442141},
{"learn":[0.03321859922],"iteration":198,"passed_time":21.44237548,"remaining_time":32.4329398},
{"learn":[0.0330932118],"iteration":199,"passed_time":21.59518198,"remaining_time":32.39277297},
{"learn":[0.03296735964],"iteration":200,"passed_time":21.71049057,"remaining_time":32.29570487},
{"learn":[0.03280660985],"iteration":201,"passed_time":21.83267466,"remaining_time":32.20859926},
{"learn":[0.03269496827],"iteration":202,"passed_time":21.95866017,"remaining_time":32.1267097},
{"learn":[0.03253775878],"iteration":203,"passed_time":22.07521558,"remaining_time":32.03070496},
{"learn":[0.03238307759],"iteration":204,"passed_time":22.18617261,"remaining_time":31.92644352},
{"learn":[0.03216513372],"iteration":205,"passed_time":22.29133349,"remaining_time":31.81384489},
{"learn":[0.03204132365],"iteration":206,"passed_time":22.39255684,"remaining_time":31.69574471},
{"learn":[0.03192148965],"iteration":207,"passed_time":22.49072822,"remaining_time":31.57352231},
{"learn":[0.03180695511],"iteration":208,"passed_time":22.58831041,"remaining_time":31.4507097},
{"learn":[0.0316369797],"iteration":209,"passed_time":22.69202183,"remaining_time":31.33660157},
{"learn":[0.03142434692],"iteration":210,"passed_time":22.80320264,"remaining_time":31.23282257},
{"learn":[0.03119338627],"iteration":211,"passed_time":22.91929884,"remaining_time":31.13565125},
{"learn":[0.03106949266],"iteration":212,"passed_time":23.03548553,"remaining_time":31.03842416},
{"learn":[0.03090301772],"iteration":213,"passed_time":23.15342162,"remaining_time":30.94335787},
{"learn":[0.03057876199],"iteration":214,"passed_time":23.27326818,"remaining_time":30.85061131},
{"learn":[0.03039746482],"iteration":215,"passed_time":23.39593933,"remaining_time":30.76132764},
{"learn":[0.03029003673],"iteration":216,"passed_time":23.50713479,"remaining_time":30.65677026},
{"learn":[0.03020137852],"iteration":217,"passed_time":23.60307259,"remaining_time":30.532415},
{"learn":[0.02999614444],"iteration":218,"passed_time":23.70275283,"remaining_time":30.41312121},
{"learn":[0.02983456757],"iteration":219,"passed_time":23.80668912,"remaining_time":30.29942251},
{"learn":[0.02956278811],"iteration":220,"passed_time":23.90010527,"remaining_time":30.17253109},
{"learn":[0.02933225392],"iteration":221,"passed_time":24.00384475,"remaining_time":30.05886865},
{"learn":[0.02912020227],"iteration":222,"passed_time":24.11431843,"remaining_time":29.95366011},
{"learn":[0.0289719109],"iteration":223,"passed_time":24.22410396,"remaining_time":29.84755666},
{"learn":[0.02886436566],"iteration":224,"passed_time":24.32658474,"remaining_time":29.73249246},
{"learn":[0.0287295077],"iteration":225,"passed_time":24.44255261,"remaining_time":29.63389121},
{"learn":[0.02861685413],"iteration":226,"passed_time":24.56496289,"remaining_time":29.54288488},
{"learn":[0.02851448913],"iteration":227,"passed_time":24.68563517,"remaining_time":29.44952968},
{"learn":[0.02832049871],"iteration":228,"passed_time":24.79562408,"remaining_time":29.34329313},
{"learn":[0.0282181818],"iteration":229,"passed_time":24.90790135,"remaining_time":29.23971028},
{"learn":[0.02811809087],"iteration":230,"passed_time":25.02699036,"remaining_time":29.14398444},
{"learn":[0.02784108126],"iteration":231,"passed_time":25.1480783,"remaining_time":29.05036631},
{"learn":[0.02767599746],"iteration":232,"passed_time":25.27806771,"remaining_time":28.96671278},
{"learn":[0.02755215842],"iteration":233,"passed_time":25.38351576,"remaining_time":28.85476578},
{"learn":[0.02733599285],"iteration":234,"passed_time":25.50942338,"remaining_time":28.76594552},
{"learn":[0.02715534146],"iteration":235,"passed_time":25.62262601,"remaining_time":28.66259859},
{"learn":[0.02704637793],"iteration":236,"passed_time":25.73346831,"remaining_time":28.55654922},
{"learn":[0.02693544575],"iteration":237,"passed_time":25.8505746,"remaining_time":28.45735523},
{"learn":[0.02678818913],"iteration":238,"passed_time":25.97696912,"remaining_time":28.36815456},
{"learn":[0.02668654594],"iteration":239,"passed_time":26.0948915,"remaining_time":28.26946579},
{"learn":[0.02659342905],"iteration":240,"passed_time":26.20495593,"remaining_time":28.16217255},
{"learn":[0.02649558426],"iteration":241,"passed_time":26.32133607,"remaining_time":28.06158969},
{"learn":[0.02631089136],"iteration":242,"passed_time":26.45465203,"remaining_time":27.97878836},
{"learn":[0.02620294784],"iteration":243,"passed_time":26.57189426,"remaining_time":27.87870873},
{"learn":[0.02607472979],"iteration":244,"passed_time":26.67912679,"remaining_time":27.76807074},
{"learn":[0.02596517246],"iteration":245,"passed_time":26.78704429,"remaining_time":27.65816768},
{"learn":[0.02580713511],"iteration":246,"passed_time":26.89316625,"remaining_time":27.54644154},
{"learn":[0.02563787066],"iteration":247,"passed_time":26.99648082,"remaining_time":27.43190793},
{"learn":[0.02549662393],"iteration":248,"passed_time":27.08595298,"remaining_time":27.30351083},
{"learn":[0.02535980664],"iteration":249,"passed_time":27.17787217,"remaining_time":27.17787217},
{"learn":[0.0251624324],"iteration":250,"passed_time":27.28239294,"remaining_time":27.06500336},
{"learn":[0.02505035142],"iteration":251,"passed_time":27.38144336,"remaining_time":26.94681727},
{"learn":[0.02490171245],"iteration":252,"passed_time":27.48620236,"remaining_time":26.83435566},
{"learn":[0.02479546576],"iteration":253,"passed_time":27.59062075,"remaining_time":26.72162482},
{"learn":[0.02466344232],"iteration":254,"passed_time":27.6968414,"remaining_time":26.61069076},
{"learn":[0.02457537997],"iteration":255,"passed_time":27.79908001,"remaining_time":26.49599814},
{"learn":[0.02440441093],"iteration":256,"passed_time":27.90191355,"remaining_time":26.38196496},
{"learn":[0.02427453174],"iteration":257,"passed_time":28.00397809,"remaining_time":26.26729728},
{"learn":[0.02419628286],"iteration":258,"passed_time":28.1154513,"remaining_time":26.16148171},
{"learn":[0.02408108779],"iteration":259,"passed_time":28.2424916,"remaining_time":26.06999225},
{"learn":[0.02399561866],"iteration":260,"passed_time":28.36829596,"remaining_time":25.9770986},
{"learn":[0.02379057493],"iteration":261,"passed_time":28.57327919,"remaining_time":25.95587957},
{"learn":[0.02364307365],"iteration":262,"passed_time":28.73534879,"remaining_time":25.89459188},
{"learn":[0.02356509348],"iteration":263,"passed_time":28.86673172,"remaining_time":25.80510866},
{"learn":[0.0234780214],"iteration":264,"passed_time":28.99082273,"remaining_time":25.7088428},
{"learn":[0.02338480623],"iteration":265,"passed_time":29.12269372,"remaining_time":25.61921177},
{"learn":[0.02327360483],"iteration":266,"passed_time":29.23705137,"remaining_time":25.51398115},
{"learn":[0.02311297426],"iteration":267,"passed_time":29.3639864,"remaining_time":25.41957032},
{"learn":[0.0230166957],"iteration":268,"passed_time":29.48114764,"remaining_time":25.31652456},
{"learn":[0.02294235617],"iteration":269,"passed_time":29.60046554,"remaining_time":25.21521139},
{"learn":[0.02280450362],"iteration":270,"passed_time":29.71642756,"remaining_time":25.11092956},
{"learn":[0.02271545617],"iteration":271,"passed_time":29.82445883,"remaining_time":24.99991402},
{"learn":[0.02265049537],"iteration":272,"passed_time":29.94102778,"remaining_time":24.89601943},
{"learn":[0.02260809274],"iteration":273,"passed_time":30.0743292,"remaining_time":24.80583358},
{"learn":[0.02252799962],"iteration":274,"passed_time":30.20061749,"remaining_time":24.70959613},
{"learn":[0.02235893741],"iteration":275,"passed_time":30.3271294,"remaining_time":24.61332241},
{"learn":[0.02227745884],"iteration":276,"passed_time":30.45919908,"remaining_time":24.52130468},
{"learn":[0.02217223423],"iteration":277,"passed_time":30.60453104,"remaining_time":24.43958954},
{"learn":[0.02208082477],"iteration":278,"passed_time":30.72792394,"remaining_time":24.34004011},
{"learn":[0.02203499746],"iteration":279,"passed_time":30.85749393,"remaining_time":24.2451738},
{"learn":[0.0219125299],"iteration":280,"passed_time":30.98492727,"remaining_time":24.14839527},
{"learn":[0.02187645088],"iteration":281,"passed_time":31.1230941,"remaining_time":24.05969686},
{"learn":[0.02173470733],"iteration":282,"passed_time":31.24789953,"remaining_time":23.96040353},
{"learn":[0.02168261305],"iteration":283,"passed_time":31.36575647,"remaining_time":23.85564576},
{"learn":[0.02163256241],"iteration":284,"passed_time":31.49228121,"remaining_time":23.75733494},
{"learn":[0.02155450931],"iteration":285,"passed_time":31.61800399,"remaining_time":23.65822676},
{"learn":[0.02147127779],"iteration":286,"passed_time":31.72330356,"remaining_time":23.54377581},
{"learn":[0.0213827525],"iteration":287,"passed_time":31.83122757,"remaining_time":23.4313203},
{"learn":[0.02131519124],"iteration":288,"passed_time":31.93131174,"remaining_time":23.31317224},
{"learn":[0.02125736482],"iteration":289,"passed_time":32.03621632,"remaining_time":23.1986394},
{"learn":[0.02114017939],"iteration":290,"passed_time":32.14990134,"remaining_time":23.09047897},
{"learn":[0.02105446638],"iteration":291,"passed_time":32.26556872,"remaining_time":22.98369279},
{"learn":[0.02101120124],"iteration":292,"passed_time":32.37605546,"remaining_time":22.87318594},
{"learn":[0.02092103396],"iteration":293,"passed_time":32.47294294,"remaining_time":22.75315049},
{"learn":[0.02084883066],"iteration":294,"passed_time":32.57720506,"remaining_time":22.63839673},
{"learn":[0.02079928847],"iteration":295,"passed_time":32.67924193,"remaining_time":22.52218025},
{"learn":[0.02073533139],"iteration":296,"passed_time":32.76853846,"remaining_time":22.3973512},
{"learn":[0.02065191495],"iteration":297,"passed_time":32.86994933,"remaining_time":22.28097236},
{"learn":[0.02059604658],"iteration":298,"passed_time":32.99886495,"remaining_time":22.18318346},
{"learn":[0.02055678183],"iteration":299,"passed_time":33.10903841,"remaining_time":22.07269228},
{"learn":[0.02043996029],"iteration":300,"passed_time":33.21820754,"remaining_time":21.9615392},
{"learn":[0.02037255963],"iteration":301,"passed_time":33.32503247,"remaining_time":21.84886235},
{"learn":[0.02028233001],"iteration":302,"passed_time":33.42613207,"remaining_time":21.73250171},
{"learn":[0.02017899542],"iteration":303,"passed_time":33.52988311,"remaining_time":21.61795095},
{"learn":[0.02008288729],"iteration":304,"passed_time":33.6313964,"remaining_time":21.50204032},
{"learn":[0.02000595662],"iteration":305,"passed_time":33.74979694,"remaining_time":21.39693009},
{"learn":[0.01994380938],"iteration":306,"passed_time":33.85783622,"remaining_time":21.28521951},
{"learn":[0.01981952797],"iteration":307,"passed_time":33.97654062,"remaining_time":21.18018116},
{"learn":[0.01971076345],"iteration":308,"passed_time":34.08823348,"remaining_time":21.07072037},
{"learn":[0.01966368827],"iteration":309,"passed_time":34.19780103,"remaining_time":20.95994257},
{"learn":[0.0195951242],"iteration":310,"passed_time":34.31816784,"remaining_time":20.85573544},
{"learn":[0.01953860021],"iteration":311,"passed_time":34.42043684,"remaining_time":20.74051963},
{"learn":[0.01948375818],"iteration":312,"passed_time":34.5317373,"remaining_time":20.63078235},
{"learn":[0.01944025641],"iteration":313,"passed_time":34.64227565,"remaining_time":20.52058366},
{"learn":[0.01924173698],"iteration":314,"passed_time":34.79061812,"remaining_time":20.43258524},
{"learn":[0.01915569991],"iteration":315,"passed_time":34.90445852,"remaining_time":20.32411509},
{"learn":[0.01908532896],"iteration":316,"passed_time":35.00631583,"remaining_time":20.20869337},
{"learn":[0.01900529609],"iteration":317,"passed_time":35.10458427,"remaining_time":20.09130294},
{"learn":[0.01894994096],"iteration":318,"passed_time":35.20831666,"remaining_time":19.97713265},
{"learn":[0.01883631186],"iteration":319,"passed_time":35.33217785,"remaining_time":19.87435004},
{"learn":[0.01875773672],"iteration":320,"passed_time":35.44549251,"remaining_time":19.76555501},
{"learn":[0.0186728535],"iteration":321,"passed_time":35.56844321,"remaining_time":19.66205867},
{"learn":[0.01862178919],"iteration":322,"passed_time":35.67928977,"remaining_time":19.55180894},
{"learn":[0.01858334325],"iteration":323,"passed_time":35.78132374,"remaining_time":19.43676845},
{"learn":[0.01849262457],"iteration":324,"passed_time":35.89318475,"remaining_time":19.32709948},
{"learn":[0.0183646676],"iteration":325,"passed_time":36.00291383,"remaining_time":19.21627916},
{"learn":[0.01827419656],"iteration":326,"passed_time":36.10620966,"remaining_time":19.10206199},
{"learn":[0.01812325584],"iteration":327,"passed_time":36.2852902,"remaining_time":19.02765218},
{"learn":[0.01804367699],"iteration":328,"passed_time":36.41456851,"remaining_time":18.92672102},
{"learn":[0.01795776561],"iteration":329,"passed_time":36.528238,"remaining_time":18.81757715},
{"learn":[0.0179173209],"iteration":330,"passed_time":36.64345256,"remaining_time":18.70919481},
{"learn":[0.01787005745],"iteration":331,"passed_time":36.75221844,"remaining_time":18.59750813},
{"learn":[0.01773549794],"iteration":332,"passed_time":36.85866366,"remaining_time":18.48467517},
{"learn":[0.01766157532],"iteration":333,"passed_time":36.96380239,"remaining_time":18.37123113},
{"learn":[0.01760684165],"iteration":334,"passed_time":37.07363179,"remaining_time":18.260147},
{"learn":[0.0175142208],"iteration":335,"passed_time":37.18954526,"remaining_time":18.15203995},
{"learn":[0.01735229234],"iteration":336,"passed_time":37.31050913,"remaining_time":18.04632934},
{"learn":[0.01724869641],"iteration":337,"passed_time":37.42463146,"remaining_time":17.9372494},
{"learn":[0.01710432085],"iteration":338,"passed_time":37.54876142,"remaining_time":17.83289259},
{"learn":[0.01704130528],"iteration":339,"passed_time":37.66902243,"remaining_time":17.72659879},
{"learn":[0.01692818916],"iteration":340,"passed_time":37.77704081,"remaining_time":17.61451463},
{"learn":[0.01682200041],"iteration":341,"passed_time":37.89347207,"remaining_time":17.5063409},
{"learn":[0.01675295633],"iteration":342,"passed_time":38.02314017,"remaining_time":17.40417786},
{"learn":[0.01667531663],"iteration":343,"passed_time":38.13581362,"remaining_time":17.29414804},
{"learn":[0.01657082664],"iteration":344,"passed_time":38.24578858,"remaining_time":17.18289052},
{"learn":[0.01650105557],"iteration":345,"passed_time":38.34960824,"remaining_time":17.06890078},
{"learn":[0.01645089657],"iteration":346,"passed_time":38.45699139,"remaining_time":16.95654087},
{"learn":[0.01639313766],"iteration":347,"passed_time":38.57256118,"remaining_time":16.84778534},
{"learn":[0.01627734142],"iteration":348,"passed_time":38.68143111,"remaining_time":16.73609197},
{"learn":[0.01621059754],"iteration":349,"passed_time":38.78401573,"remaining_time":16.62172103},
{"learn":[0.0161789565],"iteration":350,"passed_time":38.88683253,"remaining_time":16.5075158},
{"learn":[0.01609029],"iteration":351,"passed_time":38.99237857,"remaining_time":16.39452281},
{"learn":[0.01601678984],"iteration":352,"passed_time":39.10038886,"remaining_time":16.28259819},
{"learn":[0.01597868813],"iteration":353,"passed_time":39.20393347,"remaining_time":16.16885392},
{"learn":[0.01587914923],"iteration":354,"passed_time":39.3086239,"remaining_time":16.05563511},
{"learn":[0.01582243076],"iteration":355,"passed_time":39.41841777,"remaining_time":15.94452853},
{"learn":[0.0157193866],"iteration":356,"passed_time":39.52362018,"remaining_time":15.83159016},
{"learn":[0.01567319152],"iteration":357,"passed_time":39.62554288,"remaining_time":15.7173941},
{"learn":[0.01556890585],"iteration":358,"passed_time":39.74307529,"remaining_time":15.60939726},
{"learn":[0.01550514286],"iteration":359,"passed_time":39.84950138,"remaining_time":15.49702831},
{"learn":[0.01547343962],"iteration":360,"passed_time":39.9513314,"remaining_time":15.38292262},
{"learn":[0.01540466102],"iteration":361,"passed_time":40.05735827,"remaining_time":15.27048465},
{"learn":[0.01535465137],"iteration":362,"passed_time":40.17579498,"remaining_time":15.1627656},
{"learn":[0.01529111313],"iteration":363,"passed_time":40.27422186,"remaining_time":15.04751146},
{"learn":[0.01522280134],"iteration":364,"passed_time":40.37620218,"remaining_time":14.93366382},
{"learn":[0.01513365419],"iteration":365,"passed_time":40.48075247,"remaining_time":14.82082194},
{"learn":[0.0150690552],"iteration":366,"passed_time":40.59181683,"remaining_time":14.71038593},
{"learn":[0.01502826109],"iteration":367,"passed_time":40.69494263,"remaining_time":14.59709899},
{"learn":[0.0149894607],"iteration":368,"passed_time":40.8073337,"remaining_time":14.48715641},
{"learn":[0.01492740851],"iteration":369,"passed_time":40.92181518,"remaining_time":14.37793506},
{"learn":[0.01485538327],"iteration":370,"passed_time":41.03642285,"remaining_time":14.26872924},
{"learn":[0.01483250944],"iteration":371,"passed_time":41.1434137,"remaining_time":14.15687353},
{"learn":[0.01480454875],"iteration":372,"passed_time":41.24686595,"remaining_time":14.04383908},
{"learn":[0.01474086296],"iteration":373,"passed_time":41.34754898,"remaining_time":13.92992292},
{"learn":[0.01467031783],"iteration":374,"passed_time":41.4627127,"remaining_time":13.82090423},
{"learn":[0.01461341224],"iteration":375,"passed_time":41.57691,"remaining_time":13.71153415},
{"learn":[0.01457897419],"iteration":376,"passed_time":41.68602541,"remaining_time":13.60048044},
{"learn":[0.01451208393],"iteration":377,"passed_time":41.80319465,"remaining_time":13.49203637},
{"learn":[0.01445471799],"iteration":378,"passed_time":41.91128429,"remaining_time":13.38064749},
{"learn":[0.01440438093],"iteration":379,"passed_time":42.0164446,"remaining_time":13.26835093},
{"learn":[0.01438247926],"iteration":380,"passed_time":42.11603305,"remaining_time":13.15435153},
{"learn":[0.01432768198],"iteration":381,"passed_time":42.21087152,"remaining_time":13.03896031},
{"learn":[0.01428180462],"iteration":382,"passed_time":42.31837029,"remaining_time":12.92754393},
{"learn":[0.01426552634],"iteration":383,"passed_time":42.40752719,"remaining_time":12.81060717},
{"learn":[0.01419395305],"iteration":384,"passed_time":42.50823556,"remaining_time":12.69726517},
{"learn":[0.01415524447],"iteration":385,"passed_time":42.61305637,"remaining_time":12.58520318},
{"learn":[0.01411190279],"iteration":386,"passed_time":42.72103571,"remaining_time":12.47410087},
{"learn":[0.01408800196],"iteration":387,"passed_time":42.83549224,"remaining_time":12.36488436},
{"learn":[0.01403544242],"iteration":388,"passed_time":42.93846246,"remaining_time":12.25236332},
{"learn":[0.01398608735],"iteration":389,"passed_time":43.04144513,"remaining_time":12.13989478},
{"learn":[0.01394864564],"iteration":390,"passed_time":43.15540211,"remaining_time":12.03053409},
{"learn":[0.01384968269],"iteration":391,"passed_time":43.26476291,"remaining_time":11.91988366},
{"learn":[0.013775297],"iteration":392,"passed_time":43.36841813,"remaining_time":11.80768636},
{"learn":[0.01375067462],"iteration":393,"passed_time":43.45597043,"remaining_time":11.69120017},
{"learn":[0.01372618982],"iteration":394,"passed_time":43.55285274,"remaining_time":11.5773406},
{"learn":[0.01366858867],"iteration":395,"passed_time":43.64605055,"remaining_time":11.46259913},
{"learn":[0.01360992212],"iteration":396,"passed_time":43.73853153,"remaining_time":11.34778022},
{"learn":[0.01358145788],"iteration":397,"passed_time":43.83442605,"remaining_time":11.23394839},
{"learn":[0.01353362998],"iteration":398,"passed_time":43.93071963,"remaining_time":11.12030748},
{"learn":[0.01346768085],"iteration":399,"passed_time":44.03049067,"remaining_time":11.00762267},
{"learn":[0.01343713987],"iteration":400,"passed_time":44.14561495,"remaining_time":10.89879272},
{"learn":[0.01334819315],"iteration":401,"passed_time":44.25422151,"remaining_time":10.78834256},
{"learn":[0.01330756689],"iteration":402,"passed_time":44.36824125,"remaining_time":10.67920447},
{"learn":[0.01326499176],"iteration":403,"passed_time":44.46743775,"remaining_time":10.56651986},
{"learn":[0.0132046329],"iteration":404,"passed_time":44.56894278,"remaining_time":10.45444337},
{"learn":[0.01316265481],"iteration":405,"passed_time":44.67329864,"remaining_time":10.343079},
{"learn":[0.0131111758],"iteration":406,"passed_time":44.7857475,"remaining_time":10.23359832},
{"learn":[0.0130529736],"iteration":407,"passed_time":44.88861594,"remaining_time":10.12194281},
{"learn":[0.01301522685],"iteration":408,"passed_time":44.98837868,"remaining_time":10.00963927},
{"learn":[0.0129577682],"iteration":409,"passed_time":45.08091937,"remaining_time":9.89581157},
{"learn":[0.01292961017],"iteration":410,"passed_time":45.18027337,"remaining_time":9.783562848},
{"learn":[0.01283765204],"iteration":411,"passed_time":45.27488637,"remaining_time":9.670364079},
{"learn":[0.01279708759],"iteration":412,"passed_time":45.37658725,"remaining_time":9.558748404},
{"learn":[0.01269382115],"iteration":413,"passed_time":45.47612986,"remaining_time":9.44673229},
{"learn":[0.0126708224],"iteration":414,"passed_time":45.57750337,"remaining_time":9.335151293},
{"learn":[0.01259731241],"iteration":415,"passed_time":45.68541244,"remaining_time":9.224939051},
{"learn":[0.01255615842],"iteration":416,"passed_time":45.80777913,"remaining_time":9.117615511},
{"learn":[0.01254120688],"iteration":417,"passed_time":45.91670074,"remaining_time":9.007582441},
{"learn":[0.01251475926],"iteration":418,"passed_time":46.01737017,"remaining_time":8.895959389},
{"learn":[0.01246611605],"iteration":419,"passed_time":46.10942136,"remaining_time":8.782746926},
{"learn":[0.01244084672],"iteration":420,"passed_time":46.1993218,"remaining_time":8.669231407},
{"learn":[0.01238709311],"iteration":421,"passed_time":46.27927048,"remaining_time":8.553988382},
{"learn":[0.01234601037],"iteration":422,"passed_time":46.35825277,"remaining_time":8.438736319},
{"learn":[0.01231429692],"iteration":423,"passed_time":46.44034983,"remaining_time":8.32421365},
{"learn":[0.01228912832],"iteration":424,"passed_time":46.51753049,"remaining_time":8.208975968},
{"learn":[0.0122464844],"iteration":425,"passed_time":46.59703184,"remaining_time":8.094320085},
{"learn":[0.01218549269],"iteration":426,"passed_time":46.6726232,"remaining_time":7.979160407},
{"learn":[0.01213956089],"iteration":427,"passed_time":46.7482151,"remaining_time":7.864185717},
{"learn":[0.01207662291],"iteration":428,"passed_time":46.83885238,"remaining_time":7.75188466},
{"learn":[0.01204071368],"iteration":429,"passed_time":46.92282483,"remaining_time":7.638599391},
{"learn":[0.01200671645],"iteration":430,"passed_time":47.0268859,"remaining_time":7.528666188},
{"learn":[0.01196879668],"iteration":431,"passed_time":47.13256053,"remaining_time":7.419014158},
{"learn":[0.01193463898],"iteration":432,"passed_time":47.23915495,"remaining_time":7.309522822},
{"learn":[0.0118825906],"iteration":433,"passed_time":47.35248205,"remaining_time":7.201068699},
{"learn":[0.01184621908],"iteration":434,"passed_time":47.45020346,"remaining_time":7.090260287},
{"learn":[0.01178350507],"iteration":435,"passed_time":47.53648636,"remaining_time":6.97783286},
{"learn":[0.01172036252],"iteration":436,"passed_time":47.6143303,"remaining_time":6.864308487},
{"learn":[0.01168971291],"iteration":437,"passed_time":47.69425,"remaining_time":6.751240867},
{"learn":[0.01166125656],"iteration":438,"passed_time":47.77000388,"remaining_time":6.637745414},
{"learn":[0.01162656635],"iteration":439,"passed_time":47.85309482,"remaining_time":6.525422022},
{"learn":[0.01154550339],"iteration":440,"passed_time":47.94141249,"remaining_time":6.413930469},
{"learn":[0.01152305577],"iteration":441,"passed_time":48.0211444,"remaining_time":6.301417139},
{"learn":[0.01146078802],"iteration":442,"passed_time":48.12065841,"remaining_time":6.191597132},
{"learn":[0.01144006167],"iteration":443,"passed_time":48.22698359,"remaining_time":6.082682615},
{"learn":[0.01137068564],"iteration":444,"passed_time":48.33310761,"remaining_time":5.973754873},
{"learn":[0.01135867866],"iteration":445,"passed_time":48.43969743,"remaining_time":5.864896102},
{"learn":[0.01130472306],"iteration":446,"passed_time":48.5506042,"remaining_time":5.756559335},
{"learn":[0.01125937885],"iteration":447,"passed_time":48.65603904,"remaining_time":5.64757596},
{"learn":[0.0112331799],"iteration":448,"passed_time":48.76231319,"remaining_time":5.538703726},
{"learn":[0.01113934585],"iteration":449,"passed_time":48.92662827,"remaining_time":5.43629203},
{"learn":[0.01111279931],"iteration":450,"passed_time":49.05559817,"remaining_time":5.329765655},
{"learn":[0.01107257688],"iteration":451,"passed_time":49.1822552,"remaining_time":5.222894358},
{"learn":[0.01103023232],"iteration":452,"passed_time":49.28895675,"remaining_time":5.11386527},
{"learn":[0.01099546478],"iteration":453,"passed_time":49.39788025,"remaining_time":5.005071567},
{"learn":[0.01097297022],"iteration":454,"passed_time":49.49947853,"remaining_time":4.895552822},
{"learn":[0.01095926744],"iteration":455,"passed_time":49.60404469,"remaining_time":4.786355189},
{"learn":[0.01090969616],"iteration":456,"passed_time":49.79652104,"remaining_time":4.685449464},
{"learn":[0.01085143888],"iteration":457,"passed_time":49.90804028,"remaining_time":4.576719851},
{"learn":[0.01080043263],"iteration":458,"passed_time":50.01247951,"remaining_time":4.467345664},
{"learn":[0.01077107278],"iteration":459,"passed_time":50.11133804,"remaining_time":4.357507656},
{"learn":[0.01073842673],"iteration":460,"passed_time":50.20759984,"remaining_time":4.247497601},
{"learn":[0.01071459832],"iteration":461,"passed_time":50.30761529,"remaining_time":4.137855803},
{"learn":[0.01066523355],"iteration":462,"passed_time":50.408254,"remaining_time":4.028305395},
{"learn":[0.01063635176],"iteration":463,"passed_time":50.51247872,"remaining_time":3.919071625},
{"learn":[0.01061442501],"iteration":464,"passed_time":50.61606757,"remaining_time":3.809811538},
{"learn":[0.01056864929],"iteration":465,"passed_time":50.71781327,"remaining_time":3.700441312},
{"learn":[0.01054276521],"iteration":466,"passed_time":50.81747253,"remaining_time":3.590956303},
{"learn":[0.01051557134],"iteration":467,"passed_time":50.92381145,"remaining_time":3.481970014},
{"learn":[0.01045668844],"iteration":468,"passed_time":51.02608687,"remaining_time":3.372726424},
{"learn":[0.01043776923],"iteration":469,"passed_time":51.14234261,"remaining_time":3.264404848},
{"learn":[0.01040195659],"iteration":470,"passed_time":51.26336305,"remaining_time":3.156342948},
{"learn":[0.01035656001],"iteration":471,"passed_time":51.37059356,"remaining_time":3.047408093},
{"learn":[0.01032200907],"iteration":472,"passed_time":51.49181211,"remaining_time":2.939278915},
{"learn":[0.01029626866],"iteration":473,"passed_time":51.5948613,"remaining_time":2.830097877},
{"learn":[0.01026126357],"iteration":474,"passed_time":51.72199705,"remaining_time":2.722210371},
{"learn":[0.01023174493],"iteration":475,"passed_time":52.02782103,"remaining_time":2.623251481},
{"learn":[0.01019619984],"iteration":476,"passed_time":52.13678536,"remaining_time":2.513933047},
{"learn":[0.01010597591],"iteration":477,"passed_time":52.25566802,"remaining_time":2.405072587},
{"learn":[0.01008815287],"iteration":478,"passed_time":52.38745222,"remaining_time":2.296735901},
{"learn":[0.01003179725],"iteration":479,"passed_time":52.50963253,"remaining_time":2.187901355},
{"learn":[0.01001790903],"iteration":480,"passed_time":52.62412639,"remaining_time":2.078707695},
{"learn":[0.009991598356],"iteration":481,"passed_time":52.73336475,"remaining_time":1.969295779},
{"learn":[0.009950227899],"iteration":482,"passed_time":52.83917068,"remaining_time":1.859763772},
{"learn":[0.009928509211],"iteration":483,"passed_time":52.93957424,"remaining_time":1.75006857},
{"learn":[0.009914369486],"iteration":484,"passed_time":53.04298911,"remaining_time":1.640504818},
{"learn":[0.009891961179],"iteration":485,"passed_time":53.16572128,"remaining_time":1.531522835},
{"learn":[0.009870320595],"iteration":486,"passed_time":53.28474089,"remaining_time":1.42238528},
{"learn":[0.00978491004],"iteration":487,"passed_time":53.41041809,"remaining_time":1.313370937},
{"learn":[0.009775796664],"iteration":488,"passed_time":53.52597983,"remaining_time":1.204060896},
{"learn":[0.009758266126],"iteration":489,"passed_time":53.65256801,"remaining_time":1.094950368},
{"learn":[0.009716291913],"iteration":490,"passed_time":53.7535052,"remaining_time":0.985298466},
{"learn":[0.009671766313],"iteration":491,"passed_time":53.88521499,"remaining_time":0.8761823576},
{"learn":[0.009655866914],"iteration":492,"passed_time":54.00599577,"remaining_time":0.7668194126},
{"learn":[0.009640097667],"iteration":493,"passed_time":54.1255017,"remaining_time":0.6573947575},
{"learn":[0.009596253735],"iteration":494,"passed_time":54.2836686,"remaining_time":0.5483198848},
{"learn":[0.009565958508],"iteration":495,"passed_time":54.47190274,"remaining_time":0.4392895382},
{"learn":[0.009536158481],"iteration":496,"passed_time":54.66880615,"remaining_time":0.3299927937},
{"learn":[0.009522169857],"iteration":497,"passed_time":54.80287909,"remaining_time":0.2200918839},
{"learn":[0.009500587075],"iteration":498,"passed_time":54.93983901,"remaining_time":0.1100998778},
{"learn":[0.009455260131],"iteration":499,"passed_time":55.05484441,"remaining_time":0}
]}